{
  "title": "<name> और रोबो आम के पेड़ के नीचे",
  "pages": [
    {
      "text": "एक धूप भरी शाम, अपने छोटे से भारतीय शहर में, <name> बड़े आम के पेड़ के नीचे बैठी थी, अपने टूटे हुए चमकते पतंग को उदास होकर देख रही थी। “ओह नहीं,” उसने आह भरी, “ये कल के स्कूल मेले में नहीं उड़ पाएगी!”",
      "image": "/static/girl/picturebooks/sci-fi/3-5/story2/page1.png"
    },
    {
      "text": "तभी अचानक उसने व्हिर्र-व्हिर्र-क्लिक! की आवाज़ सुनी। पेड़ के पीछे से एक चमचमाता छोटा रोबोट blinking आँखों के साथ बाहर निकला। “हैलो, <name>! मैं रोबो हूँ! मदद चाहिए?” उसने खुशी से बीप किया।",
      "image": "/static/girl/picturebooks/sci-fi/3-5/story2/page2.png"
    },
    {
      "text": "<name> मुस्कुराई। “हाँ, रोबो, प्लीज़! मेरी जादुई पतंग अब न चमक रही है न उड़ रही है।” रोबो ने अपने पेट में बना नन्हा टूलबॉक्स खोला। “कोई बात नहीं! चलो इसे साथ में ठीक करते हैं!”",
      "image": "/static/girl/picturebooks/sci-fi/3-5/story2/page3.png"
    },
    {
      "text": "वह भनभनाया और ठीक करने लगा — ज़्र्र्र-टिक-टिक-टिक! — जबकि <name> पतंग पकड़कर खड़ी थी। “शायद इसे तारों की थोड़ी रोशनी चाहिए,” <name> ने कहा। रोबो ने सिर हिलाया। “या फिर थोड़ी कल्पना की छिड़कन!”",
      "image": "/static/girl/picturebooks/sci-fi/3-5/story2/page4.png"
    },
    {
      "text": "रोबो ने अपनी चमकती उंगली पतंग को छुआ, और अचानक ऊपर के सितारे और चमकने लगे। पतंग इंद्रधनुषी रंगों में झिलमिलाई और रात के आसमान में उठ गई — वूउउश! वह छतों और स्कूल के मैदान के ऊपर चमकती हुई उड़ने लगी, पीछे चमकदार रोशनी की लकीर छोड़ते हुए।",
      "image": "/static/girl/picturebooks/sci-fi/3-5/story2/page5.png"
    },
    {
      "text": "“वाह!” <name> चिल्लाई। “यह तो पहले से भी ज़्यादा सुंदर है!” रोबो खुश होकर घूम गया। “मिशन पूरा!” तभी अम्मा ने बालकनी से आवाज़ दी, “<name>! खाने का समय हो गया!” <name> ने अपने नए दोस्त को हाथ हिलाया। “थैंक यू, रोबो!”",
      "image": "/static/girl/picturebooks/sci-fi/3-5/story2/page6.png"
    },
    {
      "text": "जब रोबो आम के पेड़ के नीचे से वापस लुढ़कता हुआ जा रहा था, उसने आख़िरी बार अपनी रोशनी चमकाई — बीप-बीप! — और फुसफुसाया, “अगले आविष्कार पर मिलते हैं!” चमकती पतंग आसमान में नाचती रही और <name> मुस्कुराई, यह जानते हुए कि कल और भी रोमांचक adventures उसका इंतज़ार कर रहे हैं।",
      "image": "/static/girl/picturebooks/sci-fi/3-5/story2/page7.png"
    }
  ]
}
